nidm/__init__.py
nidm/util.py
nidm/core/BIDS_Constants.py
nidm/core/Constants.py
nidm/core/__init__.py
nidm/core/dot.py
nidm/core/provone.py
nidm/core/cde_dir/ants_cde.ttl
nidm/core/cde_dir/fs_cde.ttl
nidm/core/cde_dir/fsl_cde.ttl
nidm/core/serializers/__init__.py
nidm/core/serializers/provonerdf.py
nidm/experiment/Acquisition.py
nidm/experiment/AcquisitionObject.py
nidm/experiment/AssessmentAcquisition.py
nidm/experiment/AssessmentObject.py
nidm/experiment/CDE.py
nidm/experiment/Core.py
nidm/experiment/DataElement.py
nidm/experiment/DemographicsObject.py
nidm/experiment/Derivative.py
nidm/experiment/DerivativeObject.py
nidm/experiment/MRAcquisition.py
nidm/experiment/MRObject.py
nidm/experiment/Navigate.py
nidm/experiment/PETAcquisition.py
nidm/experiment/PETObject.py
nidm/experiment/Project.py
nidm/experiment/Query.py
nidm/experiment/Session.py
nidm/experiment/Utils.py
nidm/experiment/__init__.py
nidm/experiment/tools/__init__.py
nidm/experiment/tools/agent.ttl
nidm/experiment/tools/bidsmri2nidm.py
nidm/experiment/tools/click_base.py
nidm/experiment/tools/click_main.py
nidm/experiment/tools/csv2nidm.py
nidm/experiment/tools/nidm2bids.py
nidm/experiment/tools/nidm_affinity_propagation.py
nidm/experiment/tools/nidm_agglomerative_clustering.py
nidm/experiment/tools/nidm_concat.py
nidm/experiment/tools/nidm_convert.py
nidm/experiment/tools/nidm_gmm.py
nidm/experiment/tools/nidm_kmeans.py
nidm/experiment/tools/nidm_linreg.py
nidm/experiment/tools/nidm_merge.py
nidm/experiment/tools/nidm_query.py
nidm/experiment/tools/nidm_utils.py
nidm/experiment/tools/nidm_version.py
nidm/experiment/tools/nidm_visualize.py
nidm/experiment/tools/repronim_simple2_brainvolumes.py
nidm/experiment/tools/repronim_simple2_query.txt
nidm/experiment/tools/rest.py
nidm/experiment/tools/rest_statistics.py
nidm/experiment/tools/update_old_simple2_nidm.py
nidm/experiment/tools/utils.py
nidm/terms/__init__.py
nidm/terms/imports/crypto_import.ttl
nidm/terms/imports/dc_import.ttl
pynidm-4.2.3.dist-info/licenses/LICENSE
pynidm-4.2.3.dist-info/METADATA
pynidm-4.2.3.dist-info/WHEEL
pynidm-4.2.3.dist-info/entry_points.txt
pynidm-4.2.3.dist-info/top_level.txt
pynidm-4.2.3.dist-info/RECORD
