Metadata-Version: 2.4
Name: pynidm
Version: 4.2.3
Summary: PYNIDM: a Python NIDM library and tools
Home-page: https://github.com/incf-nidash/PyNIDM
Author: INCF-NIDASH developers
Author-email: incf-nidash-nidm@googlegroups.com
Maintainer: INCF-NIDASH developers
Maintainer-email: incf-nidash-nidm@googlegroups.com
License: Apache-2.0
Classifier: Development Status :: 3 - Alpha
Classifier: Environment :: Console
Classifier: Intended Audience :: Science/Research
Classifier: License :: OSI Approved :: Apache Software License
Classifier: Operating System :: MacOS :: MacOS X
Classifier: Operating System :: POSIX :: Linux
Classifier: Programming Language :: Python :: 3
Classifier: Topic :: Scientific/Engineering
Requires-Python: >=3.8
License-File: LICENSE
Requires-Dist: click
Requires-Dist: click-option-group
Requires-Dist: cognitiveatlas
Requires-Dist: datalad
Requires-Dist: etelemetry
Requires-Dist: numpy>=1.16.5
Requires-Dist: ontquery~=0.2.3
Requires-Dist: pyontutils
Requires-Dist: pandas
Requires-Dist: pyarrow
Requires-Dist: patsy
Requires-Dist: prov
Requires-Dist: pybids>=0.12.4
Requires-Dist: pydot~=1.4.2
Requires-Dist: pygithub
Requires-Dist: pyld<3.0,>=1.0.5
Requires-Dist: python-dateutil~=2.0
Requires-Dist: rapidfuzz
Requires-Dist: requests
Requires-Dist: scikit-learn
Requires-Dist: scipy
Requires-Dist: statsmodels
Requires-Dist: tabulate
Requires-Dist: validators
Requires-Dist: rdflib~=6.3.2
Provides-Extra: tools
Requires-Dist: matplotlib; extra == "tools"
Requires-Dist: seaborn; extra == "tools"
Provides-Extra: test
Requires-Dist: importlib-resources; python_version < "3.9" and extra == "test"
Requires-Dist: pytest; extra == "test"
Requires-Dist: pytest-cov; extra == "test"
Provides-Extra: devel
Requires-Dist: importlib-resources; python_version < "3.9" and extra == "devel"
Requires-Dist: pytest; extra == "devel"
Requires-Dist: pytest-cov; extra == "devel"
Requires-Dist: pre-commit; extra == "devel"
Dynamic: license-file
